sidetrekUtils/SidetrekModelUtils.py
sidetrekUtils/__init__.py
sidetrekUtils-0.0.14.dist-info/METADATA
sidetrekUtils-0.0.14.dist-info/WHEEL
sidetrekUtils-0.0.14.dist-info/top_level.txt
sidetrekUtils-0.0.14.dist-info/RECORD
